[
	{
		"inputs": [],
		"stateMutability": "nonpayable",
		"type": "constructor"
	},
	{
		"anonymous": false,
		"inputs": [
			{
				"indexed": true,
				"internalType": "uint256",
				"name": "date",
				"type": "uint256"
			},
			{
				"indexed": true,
				"internalType": "address",
				"name": "student",
				"type": "address"
			},
			{
				"indexed": false,
				"internalType": "bool",
				"name": "present",
				"type": "bool"
			}
		],
		"name": "AttendanceMarked",
		"type": "event"
	},
	{
		"anonymous": false,
		"inputs": [
			{
				"indexed": true,
				"internalType": "address",
				"name": "student",
				"type": "address"
			}
		],
		"name": "StudentRegistered",
		"type": "event"
	},
	{
		"inputs": [
			{
				"internalType": "uint256",
				"name": "",
				"type": "uint256"
			},
			{
				"internalType": "address",
				"name": "",
				"type": "address"
			}
		],
		"name": "attendance",
		"outputs": [
			{
				"internalType": "bool",
				"name": "",
				"type": "bool"
			}
		],
		"stateMutability": "view",
		"type": "function"
	},
	{
		"inputs": [
			{
				"internalType": "uint256",
				"name": "_date",
				"type": "uint256"
			},
			{
				"internalType": "address",
				"name": "_student",
				"type": "address"
			}
		],
		"name": "checkAttendance",
		"outputs": [
			{
				"internalType": "bool",
				"name": "",
				"type": "bool"
			}
		],
		"stateMutability": "view",
		"type": "function"
	},
	{
		"inputs": [
			{
				"internalType": "address",
				"name": "_student",
				"type": "address"
			}
		],
		"name": "getAttendanceDates",
		"outputs": [
			{
				"internalType": "uint256[]",
				"name": "",
				"type": "uint256[]"
			}
		],
		"stateMutability": "view",
		"type": "function"
	},
	{
		"inputs": [],
		"name": "getStudentList",
		"outputs": [
			{
				"internalType": "address[]",
				"name": "",
				"type": "address[]"
			}
		],
		"stateMutability": "view",
		"type": "function"
	},
	{
		"inputs": [
			{
				"internalType": "address",
				"name": "",
				"type": "address"
			}
		],
		"name": "isStudent",
		"outputs": [
			{
				"internalType": "bool",
				"name": "",
				"type": "bool"
			}
		],
		"stateMutability": "view",
		"type": "function"
	},
	{
		"inputs": [
			{
				"internalType": "uint256",
				"name": "_date",
				"type": "uint256"
			},
			{
				"internalType": "address",
				"name": "_student",
				"type": "address"
			},
			{
				"internalType": "bool",
				"name": "_present",
				"type": "bool"
			}
		],
		"name": "markAttendance",
		"outputs": [],
		"stateMutability": "nonpayable",
		"type": "function"
	},
	{
		"inputs": [
			{
				"internalType": "address",
				"name": "_student",
				"type": "address"
			}
		],
		"name": "registerStudent",
		"outputs": [],
		"stateMutability": "nonpayable",
		"type": "function"
	},
	{
		"inputs": [
			{
				"internalType": "address[]",
				"name": "_students",
				"type": "address[]"
			}
		],
		"name": "registerStudents",
		"outputs": [],
		"stateMutability": "nonpayable",
		"type": "function"
	},
	{
		"inputs": [],
		"name": "teacher",
		"outputs": [
			{
				"internalType": "address",
				"name": "",
				"type": "address"
			}
		],
		"stateMutability": "view",
		"type": "function"
	}
]